afetchx/__init__.py
afetchx/__main__.py
afetchx-1.1.1.dist-info/METADATA
afetchx-1.1.1.dist-info/WHEEL
afetchx-1.1.1.dist-info/RECORD
